post_ap/__init__.py
post_ap/data_vars_adder.py
post_ap/filter_file.py
post_ap/mc_vars_adder.py
post_ap/ntuple_filter.py
post_ap/part_vars_adder.py
post_ap/pfn_reader.py
post_ap/selector.py
post_ap/utilities.py
post_ap-0.3.6.data/scripts/list_venvs
post_ap-0.3.6.data/scripts/post_shell
post_ap-0.3.6.data/scripts/remove_job
post_ap-0.3.6.data/scripts/update_tarball
post_ap_data/__init__.py
post_ap_data/local/link_conf.yaml
post_ap_data/samples/sample_run3.yaml
post_ap_data/selection/good_runs.yaml
post_ap_data/tests/dt_2024_turbo_comp.json
post_ap_data/tests/mc_2024_turbo_comp.json
post_ap_grid/__init__.py
post_ap_grid/run_filter
post_ap_scripts/__init__.py
post_ap_scripts/dump_samples.py
post_ap_scripts/filter_ntuples.py
post_ap_scripts/job_filter_dirac.py
post_ap_scripts/job_filter_ganga.py
post_ap_scripts/lfns_from_csv.py
post_ap_scripts/list_venvs
post_ap_scripts/plot_vars.py
post_ap_scripts/post_shell
post_ap_scripts/remove_job
post_ap_scripts/save_pfns.py
post_ap_scripts/update_tarball
post_ap-0.3.6.dist-info/METADATA
post_ap-0.3.6.dist-info/WHEEL
post_ap-0.3.6.dist-info/entry_points.txt
post_ap-0.3.6.dist-info/top_level.txt
post_ap-0.3.6.dist-info/RECORD
