Metadata-Version: 2.4
Name: post_ap
Version: 0.3.6
Summary: Project with code needed to filter, trim and slim ntuples produced by AP
Requires-Dist: tqdm
Requires-Dist: apd
Requires-Dist: data_manipulation_utilities>=0.2.3
Requires-Dist: ap_utilities
Requires-Dist: rx_data
Provides-Extra: dev
Requires-Dist: pytest; extra == "dev"
